fds/__init__.py
fds/sdk/__init__.py
fds/sdk/FactSetFundamentals/__init__.py
fds/sdk/FactSetFundamentals/api_client.py
fds/sdk/FactSetFundamentals/configuration.py
fds/sdk/FactSetFundamentals/exceptions.py
fds/sdk/FactSetFundamentals/model_utils.py
fds/sdk/FactSetFundamentals/rest.py
fds/sdk/FactSetFundamentals/api/__init__.py
fds/sdk/FactSetFundamentals/api/batch_processing_api.py
fds/sdk/FactSetFundamentals/api/company_reports_api.py
fds/sdk/FactSetFundamentals/api/fact_set_fundamentals_api.py
fds/sdk/FactSetFundamentals/api/fundamentals_point_in_time_api.py
fds/sdk/FactSetFundamentals/api/metrics_api.py
fds/sdk/FactSetFundamentals/api/segments_api.py
fds/sdk/FactSetFundamentals/apis/__init__.py
fds/sdk/FactSetFundamentals/model/__init__.py
fds/sdk/FactSetFundamentals/model/address.py
fds/sdk/FactSetFundamentals/model/batch.py
fds/sdk/FactSetFundamentals/model/batch_error_object.py
fds/sdk/FactSetFundamentals/model/batch_result.py
fds/sdk/FactSetFundamentals/model/batch_result_response.py
fds/sdk/FactSetFundamentals/model/batch_status.py
fds/sdk/FactSetFundamentals/model/batch_status_response.py
fds/sdk/FactSetFundamentals/model/company_fundamentals_response.py
fds/sdk/FactSetFundamentals/model/company_report_error_object.py
fds/sdk/FactSetFundamentals/model/dividend.py
fds/sdk/FactSetFundamentals/model/error_object.py
fds/sdk/FactSetFundamentals/model/error_object_links.py
fds/sdk/FactSetFundamentals/model/error_response.py
fds/sdk/FactSetFundamentals/model/exchange.py
fds/sdk/FactSetFundamentals/model/financial_response.py
fds/sdk/FactSetFundamentals/model/financials.py
fds/sdk/FactSetFundamentals/model/fiscal_period.py
fds/sdk/FactSetFundamentals/model/frequency_enum.py
fds/sdk/FactSetFundamentals/model/fundamental.py
fds/sdk/FactSetFundamentals/model/fundamental_fiscal_period.py
fds/sdk/FactSetFundamentals/model/fundamental_request_body.py
fds/sdk/FactSetFundamentals/model/fundamental_value.py
fds/sdk/FactSetFundamentals/model/fundamentals.py
fds_sdk_factsetfundamentals-3.1.0.dist-info/licenses/LICENSE
fds_sdk_factsetfundamentals-3.1.0.dist-info/METADATA
fds_sdk_factsetfundamentals-3.1.0.dist-info/WHEEL
fds_sdk_factsetfundamentals-3.1.0.dist-info/top_level.txt
fds_sdk_factsetfundamentals-3.1.0.dist-info/RECORD
